{
  "persons": [
    {
      "name": "Dan Abramov",
      "number": "12-43-234345",
      "id": 3
    },
    {
      "name": "Mary Poppendieck",
      "number": "39-23-6423122",
      "id": 4
    },
    {
      "name": "mac",
      "number": "1234",
      "id": 7
    },
    {
      "name": "tocmac",
      "number": "89999",
      "id": 8
    },
    {
      "name": "koka",
      "number": "4444",
      "id": 9
    },
    {
      "name": "koks",
      "number": "123",
      "id": 10
    },
    {
      "name": "njkj",
      "number": "123",
      "id": 11
    },
    {
      "name": "njkj smf ,",
      "number": "123",
      "id": 12
    },
    {
      "name": "njkjff3",
      "number": "123",
      "id": 13
    },
    {
      "name": "223",
      "number": "",
      "id": 14
    }
  ]
}